Metadata-Version: 2.1
Name: odoo-addon-account_product_fiscal_classification
Version: 16.0.1.2.0.1
Summary: Simplify taxes management for products
Home-page: https://github.com/OCA/account-fiscal-rule
Author: Akretion,GRAP,La Louve,Odoo Community Association (OCA)
Author-email: support@odoo-community.org
License: AGPL-3
Classifier: Programming Language :: Python
Classifier: Framework :: Odoo
Classifier: Framework :: Odoo :: 16.0
Classifier: License :: OSI Approved :: GNU Affero General Public License v3
Requires-Python: >=3.10
Requires-Dist: odoo-addon-account-usability<16.1dev,>=16.0dev
Requires-Dist: odoo<16.1dev,>=16.0a
